guardrails/__init__.py
guardrails/exceptions.py
guardrails/permissions.py
guardrails/validators.py
py_guardrails-0.1.0.dist-info/licenses/LICENSE
py_guardrails-0.1.0.dist-info/METADATA
py_guardrails-0.1.0.dist-info/WHEEL
py_guardrails-0.1.0.dist-info/top_level.txt
py_guardrails-0.1.0.dist-info/RECORD
