Metadata-Version: 2.4
Name: py-guardrails
Version: 0.1.0
Summary: Lightweight validation and permission helpers for Python backends
Author-email: Tamal Majumdar <tamalcrj2002@gmail.com>
License: MIT
Requires-Python: >=3.9
License-File: LICENSE
Provides-Extra: dev
Requires-Dist: pytest; extra == "dev"
Dynamic: license-file
